meowcorp/__init__.py
meowcorp/commands/__init__.py
meowcorp/commands/commands_handler.py
meowcorp/conf/__init__.py
meowcorp/conf/project_tempalte/.env-tpl
meowcorp/conf/project_tempalte/__init__.py
meowcorp/conf/project_tempalte/main.py-tpl
meowcorp/conf/project_tempalte/models/__init__.py-tpl
meowcorp/conf/project_tempalte/models/models.py-tpl
meowcorp/conf/project_tempalte/settings/__init__.py-tpl
meowcorp/conf/project_tempalte/settings/logging_config.py-tpl
meowcorp/conf/project_tempalte/settings/settings.py-tpl
meowcorp/conf/project_tempalte/telegram/__init__.py-tpl
meowcorp/conf/project_tempalte/telegram/bot.py-tpl
meowcorp/conf/project_tempalte/telegram/branches/BranchExample.py-tpl
meowcorp/conf/project_tempalte/telegram/branches/__init__.py-tpl
meowcorp/conf/project_tempalte/telegram/branches/start/BranchExample.py-tpl
meowcorp/conf/project_tempalte/telegram/callbacks/TestCallback.py-tpl
meowcorp/conf/project_tempalte/telegram/callbacks/__init__.py-tpl
meowcorp/conf/project_tempalte/telegram/status/__init__.py-tpl
meowcorp/conf/project_tempalte/telegram/status/status_branch.py-tpl
meowcorp/conf/project_tempalte/telegram/status/status_callback.py-tpl
meowcorp/exceptions/__init__.py
meowcorp/exceptions/keyboard.py
meowcorp/exceptions/status.py
meowcorp/exceptions/validation.py
meowcorp/factory/__init__.py
meowcorp/factory/factory.py
meowcorp/handlers/__init__.py
meowcorp/handlers/args.py
meowcorp/interfaces/IBranch.py
meowcorp/interfaces/ICallback.py
meowcorp/interfaces/__init__.py
meowcorp/keyboard/__init__.py
meowcorp/keyboard/utils.py
meowcorp/status/__init__.py
meowcorp/status/status.py
meowcorp-0.1.3.dist-info/LICENSE
meowcorp-0.1.3.dist-info/METADATA
meowcorp-0.1.3.dist-info/WHEEL
meowcorp-0.1.3.dist-info/entry_points.txt
meowcorp-0.1.3.dist-info/top_level.txt
meowcorp-0.1.3.dist-info/RECORD
