Metadata-Version: 2.1
Name: meowcorp
Version: 0.1.3
Summary: Add-on to the library of aiogram
Home-page: https://github.com/EluciferE/meowcorp/
License: UNKNOWN
Platform: UNKNOWN
Classifier: Programming Language :: Python :: 3.7
Classifier: License :: OSI Approved :: GNU General Public License v3 (GPLv3)
License-File: LICENSE
Requires-Dist: python-dotenv (~=0.21.0)
Requires-Dist: sqlalchemy (~=1.4.39)
Requires-Dist: psycopg2 (~=2.9.5)
Requires-Dist: aiogram (~=2.23.1)
